{
  "0": {
    "basicblocks": 1,
    "calls": "7 10 5 9 1 8 6 2 3 4",
    "file": "LeNet_wrapper.cpp",
    "fileloc": 3,
    "instructions": 99,
    "name": "LeNet_wrapper",
    "total_instructions": 6901
  },
  "1": {
    "basicblocks": 68,
    "calls": "",
    "file": "stream_convolution_slideWindow.h",
    "fileloc": 60,
    "instructions": 353,
    "loads": {
      "L": 13
    },
    "name": "SCIG<5, 20, 12, 50, 8, 0>",
    "stores": {
      "L": 13
    },
    "total_instructions": 616
  },
  "10": {
    "basicblocks": 68,
    "calls": "",
    "file": "stream_convolution_slideWindow.h",
    "fileloc": 60,
    "instructions": 353,
    "loads": {
      "L": 13
    },
    "name": "SCIG<5, 1, 28, 20, 24, 0>",
    "stores": {
      "L": 13
    },
    "total_instructions": 616
  },
  "2": {
    "basicblocks": 86,
    "calls": "",
    "file": "fully_connected.h",
    "fileloc": 6,
    "instructions": 388,
    "loads": {
      "G": 8,
      "L": 17
    },
    "name": "FC<1, 800, 500>",
    "stores": {
      "G": 9,
      "L": 13
    },
    "total_instructions": 833
  },
  "3": {
    "basicblocks": 86,
    "calls": "",
    "file": "fully_connected.h",
    "fileloc": 6,
    "instructions": 388,
    "loads": {
      "G": 8,
      "L": 17
    },
    "name": "FC<1, 500, 10>",
    "stores": {
      "G": 9,
      "L": 13
    },
    "total_instructions": 833
  },
  "4": {
    "basicblocks": 22,
    "calls": "",
    "file": "axi_dma_master.h",
    "fileloc": 2,
    "instructions": 225,
    "loads": {
      "L": 18
    },
    "name": "AXI_DMA_MASTER",
    "stores": {
      "L": 30
    },
    "total_instructions": 365
  },
  "5": {
    "basicblocks": 86,
    "calls": "",
    "file": "fixed_point_stream_convolution.h",
    "fileloc": 7,
    "instructions": 388,
    "loads": {
      "G": 8,
      "L": 17
    },
    "name": "SMM<1, 25, 20>",
    "stores": {
      "G": 9,
      "L": 13
    },
    "total_instructions": 828
  },
  "6": {
    "basicblocks": 132,
    "calls": "",
    "file": "pool.h",
    "fileloc": 58,
    "instructions": 497,
    "loads": {
      "G": 3,
      "L": 27
    },
    "name": "pool<2, 50, 8>",
    "stores": {
      "G": 4,
      "L": 26
    },
    "total_instructions": 778
  },
  "7": {
    "basicblocks": 16,
    "calls": "",
    "file": "axi_dma_slave.h",
    "fileloc": 2,
    "instructions": 178,
    "loads": {
      "L": 10
    },
    "name": "AXI_DMA_SLAVE",
    "stores": {
      "L": 10
    },
    "total_instructions": 318
  },
  "8": {
    "basicblocks": 86,
    "calls": "",
    "file": "fixed_point_stream_convolution.h",
    "fileloc": 7,
    "instructions": 388,
    "loads": {
      "G": 8,
      "L": 17
    },
    "name": "SMM<1, 500, 50>",
    "stores": {
      "G": 9,
      "L": 13
    },
    "total_instructions": 828
  },
  "9": {
    "basicblocks": 132,
    "calls": "",
    "file": "pool.h",
    "fileloc": 58,
    "instructions": 497,
    "loads": {
      "G": 3,
      "L": 27
    },
    "name": "pool<2, 20, 24>",
    "stores": {
      "G": 4,
      "L": 26
    },
    "total_instructions": 778
  }
}